<fileinfo>
    <file>
        <source>${source}</source>
        <destination>${destination}</destination>
        <type>plain</type>
        <uuidstructure>84e91b10-bd63-11e6-9178-8cdcd4d49146</uuidstructure>
        <uuidresource>84e91b11-bd63-11e6-9178-8cdcd4d49146</uuidresource>
        <datelastmodified>${datelastmodified}</datelastmodified>
        <userlastmodified>Admin</userlastmodified>
        <datecreated>${datecreated}</datecreated>
        <usercreated>Admin</usercreated>
        <flags>0</flags>
        <properties/>
        <relations/>
        <accesscontrol/>
    </file>
    <siblingcount>1</siblingcount>
</fileinfo>
